Workbook

Sheet Case Study
A1: COST ESTIMATOR ACTIVITY | Codebasics — Digital Asset Assistant (AI Cost Model)
A3: 🕐 Time Budget: 30 minutes | Read the case carefully before moving to the Assumptions & Cost Estimator sheets
A5: ABOUT THE ENGAGEMENT — AI PRODUCT MANAGEMENT
A6: 1. This is the AI cost-estimation exercise for the Codebasics Digital Asset Assistant capstone. 2. The AI PM's job is to translate Codebasics' asset-management pain points into scoped AI features and estimate the monthly API cost before build. 3. Each feature is priced with token-based model pricing, matched to task complexity — you don't pay flagship prices for a simple job.
A10: THE ORGANISATION — Codebasics
A11: Codebasics is an ed-tech company that began as a YouTube channel in 2016 and grew into a full learning platform — courses, bootcamps, YouTube tutorials and community content. A decade of production has left thousands of digital assets (thumbnails, slide decks, PDFs, promo creatives, videos) scattered across drives with no catalog. Founder Dhaval Patel wants an AI assistant that lets any team member find the right asset by simply describing it — and needs an estimated monthly API cost model before committing to build.
A15: DISCOVERY CONVERSATION | AI PM speaks to Dhaval Patel (Codebasics Founder)
A16: AI PM
A17: Dhaval, before we talk solution, help me understand the day-to-day friction. What are the top three things slowing your content teams down when it comes to finding and reusing assets?
A21: Dhaval Patel (Codebasics Founder)
A22: First — nobody can search inside our files. A thumbnail, a slide deck, a PDF: the filename rarely says what's actually in it, and you obviously can't search the text inside an image or a slide. We need something that automatically reads what's inside every asset and describes it, so the content itself becomes searchable.
A26: AI PM
... A72: Go to the Summary tab. Enter the total estimated monthly cost per feature and compute the grand total. Be prepared to share your numbers and your model choices with the class.

Sheet Assumptions
A1: Assumptions Sheet | Fill in model pricing from openai.com/api/pricing
A3: Instructions: Visit openai.com/api/pricing or anyother provider → find the model you want to use for each feature → fill in the yellow cells below. You may add more rows for additional models.
A5: TEXT / REASONING MODELS — Prices per 1 Million Tokens (USD)
A6: Model Name | B6: Model ID | C6: Input ($/1M tokens) | D6: Cached Input ($/1M tokens) | E6: Output ($/1M tokens) | F6: Notes / Use Case
A7: GPT-5.4 Nano | B7: gpt-5.4-nano | C7: 0.2 | D7: 0.02 | E7: 1.25 | F7: Auto-Tagging / Classification — cheapest model; simple, high-volume tag assignment
A8: GPT-5.4 Mini | B8: gpt-5.4-mini | C8: 0.75 | D8: 0.075 | E8: 4.5 | F8: Content Extraction & Captioning — vision-capable; reads images/slides/PDFs → caption + fields
A9: GPT-5.4 Mini | B9: gpt-5.4-mini | C9: 0.75 | D9: 0.075 | E9: 4.5 | F9: Natural-Language Search & Clarification — ranks + explains matches, asks clarifying questions
A10: GPT-5.4 Embed | B10: gpt-5.4-embed | C10: 0.1 | D10: — | E10: 0 | F10: Semantic + duplicate search — embeds each asset & query (input-only, very low cost)
A15: 💡 Tip: 1 token ≈ 0.75 words | A 200-word prompt ≈ ~267 input tokens | A 100-word response ≈ ~133 output tokens
A18: WHY THESE MODELS WERE CHOSEN (match model to task complexity — don't pay flagship prices for simple jobs)
A20: Feature | B20: Model chosen | C20: Reasoning + alternative considered
A21: Auto-Tagging (Classification) | B21: gpt-5.4-nano | C21: Simple mapping into a fixed set of asset types (thumbnail, slide, banner…) and topics — no reasoning needed, and it runs on every asset so the cheapest model matters most.
A22: Content Extraction & Captioning | B22: gpt-5.4-mini | C22: Needs vision to read thumbnails, slides and scanned PDFs and emit a caption + structured tags. Flagship considered for max accuracy but ~3x+ the cost for marginal gain at this scale.
A23: Natural-Language Search | B23: gpt-5.4-mini | C23: Conversational-quality ranking explanations and clarifying questions at low cost; upgrade to flagship only if users report poor relevance.
A25: Note: prices follow the provided GPT-5.4 rate card (cells C7:E10). Cheaper levers: Batch API −50% for non-real-time ingestion (extraction + tagging); prompt caching −75–90% on the repeated search system prompt. Verify live rates before finalising.
A28: STEP 1 — REQUIREMENT → AI FEATURE MAPPING (map first, then price)
A30: Business need (Codebasics) | B30: Mapped AI feature / use case | C30: Why it maps there
A31: Filenames don't describe content; can't search inside images, slides or PDFs | B31: Content Extraction & Captioning (Vision / OCR) | C31: Reads the pixels/text inside each asset and produces a searchable caption + extracted fields.
A32: Thousands of assets are inconsistently labelled by type and topic | B32: Auto-Tagging (Classification) | C32: Assigns each asset to a fixed set of types and topics — a classic classification task.
A33: People can't find assets; they browse, ask a colleague, or rebuild | B33: Natural-Language Search (Conversational / RAG) | C33: Interprets a plain-language request, retrieves and ranks candidates, and asks a clarifying question when ambiguous.
A34: Decoys not used: Sentiment Analysis, Audio Transcription, Summarization — none of the three needs match these. Embeddings power retrieval but are a low-cost supporting component (noted separately).

Sheet Cost Estimator
A1: Cost Estimator | Codebasics Digital Asset Assistant – AI Product Cost Model
A3: Instructions: Fill in one row per AI feature. Use the Assumptions sheet for model pricing. Build the cost formula yourself: Monthly Cost ($) = (Monthly Volume × Avg Tokens / 1,000,000) × Rate ($/1M)
A5: CODEBASICS DIGITAL ASSET ASSISTANT – AI FEATURE COST ESTIMATION
A6: Feature / Use Case | B6: Category | C6: Monthly Volume | D6: Avg Input Tokens / req | E6: Avg Output Tokens / req | F6: Model Selected (from Assumptions) | G6: Monthly Input Cost ($) | H6: Monthly Output Cost ($) | I6: Total Monthly Cost ($)
A7: Auto-Tagging & Classification (asset type + topic) | B7: Classification | C7: 1500 | D7: 400 | E7: 20 | F7: gpt-5.4-nano | G7: =(C7*D7/1000000)*Assumptions!$C$7 -> 0.12 | H7: =(C7*E7/1000000)*Assumptions!$E$7 -> 0.0375 | I7: =G7+H7 -> 0.1575
A8: Content Extraction & Captioning (read inside images / slides / PDFs) | B8: OCR / Vision Extraction | C8: 1500 | D8: 1200 | E8: 300 | F8: gpt-5.4-mini | G8: =(C8*D8/1000000)*Assumptions!$C$8 -> 1.35 | H8: =(C8*E8/1000000)*Assumptions!$E$8 -> 2.025 | I8: =G8+H8 -> 3.375
A9: Natural-Language Search & Clarification | B9: Conversational AI / RAG | C9: 12000 | D9: 1500 | E9: 200 | F9: gpt-5.4-mini | G9: =(C9*D9/1000000)*Assumptions!$C$9 -> 13.5 | H9: =(C9*E9/1000000)*Assumptions!$E$9 -> 10.8 | I9: =G9+H9 -> 24.3
A10: TOTAL MONTHLY COST | G10: =SUM(G7:G9) -> 14.97 | H10: =SUM(H7:H9) -> 12.8625 | I10: =SUM(I7:I9) -> 27.8325
A12: FORMULA REFERENCE
A13: Monthly Input Cost ($) = (Monthly Volume × Avg Input Tokens per Req) ÷ 1,000,000 × Input Rate ($/1M) from Assumptions sheet
A14: Monthly Output Cost ($) = (Monthly Volume × Avg Output Tokens per Req) ÷ 1,000,000 × Output Rate ($/1M) from Assumptions sheet
A15: Total Monthly Cost ($) = Monthly Input Cost + Monthly Output Cost
A16: Volume guidance for Codebasics: New/updated assets ≈ 1,000–2,000/month (tagging + extraction each run once per asset) | Searches ≈ 10,000–15,000/month (~40 internal users).
A18: HOW THE MONTHLY VOLUMES WERE DERIVED
A19: Driver | B19: Clue from the case study + assumption | F19: Calculation | G19: Raw result | H19: Value used
A20: Tagging & Extraction | B20: 'Thousands of assets, more added every week' → ~1,500 new/updated assets/month; each is tagged once and captioned once. | F20: ~1,500 / month (both) | G20: =1500 -> 1500 | H20: =C7 -> 1500
A21: Natural-Language Search | B21: ~40 internal users × ~300 searches/user/month → midpoint of the 10k–15k guidance band. | F21: 40 × 300 | G21: =40*300 -> 12000 | H21: =C9 -> 12000
A22: Embeddings (supporting) | B22: Embed each new asset + each query for semantic & duplicate search — input-only, ≈ $0.11/mo; kept as a note, not a line. | F22: 1,500 + 12,000 | G22: =1500+12000 -> 13500 | H22: ≈ $0.11 / mo
A24: HOW THE TOKENS PER REQUEST WERE DERIVED (tip: tokens = words ÷ 0.75)
A25: Item | B25: What the text is | F25: Words assumed (You can change, randomply kept) | G25: Tokens (= words ÷ 0.75) | H25: Value used
A26: Tag – input | B26: extracted text snippet + classify prompt | F26: 300 | G26: =F26/0.75 -> 400 | H26: =D7 -> 400
A27: Tag – output | B27: asset type + topic labels (JSON) | F27: 15 | G27: =F27/0.75 -> 20 | H27: =E7 -> 20
A28: Extract – input | B28: thumbnail / slide / PDF image + instruction (vision) | F28: 900 | G28: =F28/0.75 -> 1200 | H28: =D8 -> 1200
A29: Extract – output | B29: caption + extracted text + tags (JSON) | F29: 225 | G29: =F29/0.75 -> 300 | H29: =E8 -> 300
A30: Search – input | B30: query + system prompt + top-k retrieved snippets (RAG) | F30: 1125 | G30: =F30/0.75 -> 1500 | H30: =D9 -> 1500
A31: Search – output | B31: ranked explanation + clarifying question | F31: 150 | G31: =F31/0.75 -> 200 | H31: =E9 -> 200
A33: ONE-TIME INITIAL INDEXING (BACKFILL)
A34: Index the existing ~20,000-asset library once (extraction + tagging + embeddings). Real-time search cost is separate/monthly.
A35: Estimated one-time backfill cost ($) | I35: =(20000*1200/1000000*Assumptions!C8)+(20000*300/1000000*Assumptions!E8)+(20000*400/1000000*Assumptions!C7)+(20000*20/1000000*Assumptions!E7)+(20000*500/1000000*0.1) -> 48.1

Sheet Summary
A1: Summary | Model Selection & Cost Overview
A3: Instructions: Fill in your model choices and total monthly cost per feature from the Cost Estimator sheet. Be ready to share with the class.
A5: CODEBASICS – AI PRODUCT COST SUMMARY
A6: Feature / Use Case | B6: Mapped AI Use Case | C6: Model Selected | D6: Total Monthly Cost ($) | E6: Rationale for Model Choice
A7: Auto-Tagging & Classification | B7: Classification | C7: gpt-5.4-nano | D7: ='Cost Estimator'!I7 -> 0.1575 | E7: Simple, high-volume tag assignment — the cheapest model is enough; no reasoning model needed.
A8: Content Extraction & Captioning | B8: OCR / Vision Extraction | C8: gpt-5.4-mini | D8: ='Cost Estimator'!I8 -> 3.375 | E8: Vision to read images / slides / PDFs + structured caption; mini balances accuracy and cost at scale.
A9: Natural-Language Search & Clarification | B9: Conversational AI / RAG | C9: gpt-5.4-mini | D9: ='Cost Estimator'!I9 -> 24.3 | E9: Conversational-quality ranking + clarifying questions at low cost; upgrade only on quality complaints.
A10: TOTAL ESTIMATED MONTHLY API COST | D10: =SUM(D7:D9) -> 27.8325
A12: CLASS DISCUSSION PROMPTS
A13: 1. Which model did you choose for auto-tagging and why? Is a reasoning/flagship model necessary for fixed-category tagging?
A14: 2. How did you estimate monthly volume for extraction and tagging given a library of thousands of assets plus new ones each week?
A15: 3. For natural-language search, how did you balance answer quality vs. cost? Would you cache the system prompt or trim RAG context?
A16: 4. What changes if ingestion (extraction + tagging) runs on the Batch API at −50%? What about prompt caching on the search prompt?
A17: 5. Given the tiny API cost versus the staff time saved, how would you frame the ROI to the founder?
A19: KEY INSIGHTS
A20: Assumed monthly AI budget for the assistant | D20: 100
A21: Insight | C21: Calculation | D21: Result
A22: Content Extraction share of total cost | C22: =D8 / D10 -> 0.12126112 | D22: =D8/D10 -> 0.12126112
A23: Natural-Language Search share of total cost | C23: =D9 / D10 -> 0.87308003 | D23: =D9/D10 -> 0.87308003
A24: Auto-Tagging share of total cost | C24: =D7 / D10 -> 0.0056588521 | D24: =D7/D10 -> 0.0056588521
A25: Budget used | C25: =D10 / D20 -> 0.278325 | D25: =D10/D20 -> 0.278325
A26: Saving if Batch API (−50%) on ingestion (tagging + extraction) | C26: =(D7 + D8) * 50% -> 1.76625 | D26: =(D7+D8)*0.5 -> 1.76625
A27: One-time initial indexing (backfill ~20,000 assets) | C27: extract + tag + embed, one-off | D27: ='Cost Estimator'!I35 -> 48.1
